odoo/addons/fieldservice_kanban_info/README.rst
odoo/addons/fieldservice_kanban_info/__init__.py
odoo/addons/fieldservice_kanban_info/__manifest__.py
odoo/addons/fieldservice_kanban_info/i18n/ca.po
odoo/addons/fieldservice_kanban_info/i18n/es.po
odoo/addons/fieldservice_kanban_info/i18n/fieldservice_kanban_info.pot
odoo/addons/fieldservice_kanban_info/i18n/it.po
odoo/addons/fieldservice_kanban_info/models/__init__.py
odoo/addons/fieldservice_kanban_info/models/fsm_order.py
odoo/addons/fieldservice_kanban_info/models/res_config_settings.py
odoo/addons/fieldservice_kanban_info/readme/CONTRIBUTORS.md
odoo/addons/fieldservice_kanban_info/readme/DESCRIPTION.md
odoo/addons/fieldservice_kanban_info/readme/USAGE.md
odoo/addons/fieldservice_kanban_info/static/description/icon.png
odoo/addons/fieldservice_kanban_info/static/description/index.html
odoo/addons/fieldservice_kanban_info/tests/__init__.py
odoo/addons/fieldservice_kanban_info/tests/test_fieldservice_kanban_info.py
odoo/addons/fieldservice_kanban_info/views/fsm_order.xml
odoo/addons/fieldservice_kanban_info/views/res_config_settings_views.xml
odoo_addon_fieldservice_kanban_info-18.0.1.0.1.dist-info/METADATA
odoo_addon_fieldservice_kanban_info-18.0.1.0.1.dist-info/WHEEL
odoo_addon_fieldservice_kanban_info-18.0.1.0.1.dist-info/top_level.txt
odoo_addon_fieldservice_kanban_info-18.0.1.0.1.dist-info/RECORD
